Workbook

Sheet Sheet1
A1: SK MOBILE SHOP | C1: Financial Business Dashboard
A3: OPENING BALANCE | B3: TOTAL INCOME | C3: TOTAL EXPENSE | D3: TOTAL WITHDRAWAL | E3: DAMAGE & LOSS | F3: NET PROFIT
A4: 910000 | B4: =A12+B12+C12 -> 127352.03 | C4: =Sheet5!H34 -> 1139 | D4: =Sheet6!S34 -> 110500 | E4: =Sheet5!N34 -> 80 | F4: =A4+B4-C4-D4-E4 -> 925633.03
A6: Service-Wise Net Profit Tracker | E6: Payment Mode Summary
E7: Cash & Portal Balance | F7: =A4+A12+B15+C15+D12-C4-D4-E4-F9 -> 953279.03
A8: Recharge & | B8: Mobile | C8: MOBILE & | D8: EXTRA INCOME
A9: Transfer | B9: Repairing | C9: ACCESSORIES | E9: Bank Balance | F9: =Sheet6!O34 -> 91627
A10: Profit | B10: Profit | C10: Profit
E11: UDHAR + | F11: =Sheet6!I34 -> 29499
A12: =Sheet2!O37+Sheet3!T37 -> 49142.03 | B12: =Sheet4!E34 -> 39325 | C12: =Sheet4!I34 -> 38885 | D12: =Sheet4!L34 -> 58576
E13: PARTY PAYMENT - | F13: =Sheet6!E34 -> 44093
B14: TOTAL REPAIR | C14: TOTAL MOBILE, ACCESS | E14: TOTAL | F14: =F7+F9-F11-F13 -> 971314.03
B15: =Sheet4!C34 -> 74490 | C15: =Sheet4!G34 -> 64417

Sheet Sheet2
A1: MONEY TRANSFER REPORT
B2: DMT 99 | G2: DMT 86 | M2: IME
A4: DATE | B4: DMT | C4: AEPS | D4: NEPAL | E4: BILL PAY | F4: QR | G4: DMT | H4: AEPS | I4: CREDIT | J4: BILL PAY | K4: wallet | L4: QR | M4: NEPAL | N4: AEPS | O4: TOTAL
F5: UPI | K5: ppi | L5: UPI
A6: 46143 | O6: 0
A7: 46144 | O7: 0
A8: 46145 | O8: 0
A9: 46146 | O9: 0
A10: 46147 | O10: 0
A11: 46148 | O11: 0
A12: 46149 | O12: 0
A13: 46150 | O13: 0
A14: 46151 | B14: 314.53 | C14: 121.76 | D14: 398.4 | E14: 0 | F14: 0 | G14: 224.94 | H14: 20.73 | I14: 0 | J14: 0 | K14: 190 | L14: 16 | M14: 0 | N14: 0 | O14: 1286.36
A15: 46152 | B15: 279.81 | C15: 243.8 | D15: 1628.52 | E15: 0 | F15: 0 | G15: 0 | H15: 0 | I15: 1244.5 | J15: 0 | K15: 0 | L15: 179.59 | M15: 218.64 | N15: 0 | O15: 3794.86
A16: 46153 | B16: 507.08 | C16: 148.42 | D16: 1861.84 | E16: 0 | F16: 0 | G16: 137.57 | H16: 219.6 | I16: 0 | J16: 7.99 | K16: 0 | L16: 627.35 | M16: 327.96 | N16: 0 | O16: 3837.81
A17: 46154 | B17: 327.42 | C17: 212.52 | D17: 2973.52 | E17: 0 | F17: 0 | G17: 94.23 | H17: 32.69 | I17: 0 | J17: 0 | K17: 70 | L17: 178.91 | M17: 437.28 | N17: 0 | O17: 4326.57
A18: 46155 | B18: 317.7 | C18: 215.76 | D18: 1702.42 | E18: 0 | F18: 0 | G18: 116.25 | H18: 115.43 | I18: 0 | J18: 0 | K18: 239 | L18: 79.94 | M18: 109.32 | N18: 0 | O18: 2895.82
A19: 46156 | B19: 189.59 | C19: 419.33 | D19: 1494 | E19: 20 | F19: 0 | G19: 49.28 | H19: 95.43 | I19: 0 | J19: 0 | K19: 220 | L19: 231.43 | M19: 874.56 | N19: 0 | O19: 3593.62
A20: 46157 | B20: 474.69 | C20: 1111.45 | D20: 996 | E20: 0 | F20: 0 | G20: 0 | H20: 0 | I20: 0 | J20: 0 | K20: 0 | L20: 450 | M20: 0 | N20: 0 | O20: 3032.14
A21: 46158 | B21: 117.98 | C21: 142.54 | D21: 498 | E21: 0 | F21: 0 | G21: 75.89 | H21: 455.01 | I21: 0 | J21: 0 | K21: 90.9 | L21: 96.42 | M21: 437.28 | N21: 0 | O21: =SUM(B21:N21) -> 1914.02
A22: 46159 | B22: 256.77 | C22: 906.93 | D22: 1095.6 | E22: 0 | F22: 0 | G22: 0 | H22: 0 | I22: 0 | J22: 0 | K22: 181.5 | L22: 123.9 | M22: 109.32 | N22: 0 | O22: =SUM(B22:N22) -> 2674.02
A23: 46160 | B23: 225.6 | C23: 665.72 | D23: 1195.2 | E23: 10 | F23: 0 | G23: 194.84 | H23: 207.97 | I23: 0 | J23: 793 | K23: 815.75 | L23: 63 | M23: 109.32 | N23: 0 | O23: =SUM(B23:N23) -> 4280.4
A24: 46161 | B24: 217.94 | C24: 534.86 | D24: 1095.6 | E24: 0 | F24: 0 | G24: 147.97 | H24: 239.98 | I24: 0 | J24: 0 | K24: 0 | L24: 0 | M24: 109.32 | N24: 0 | O24: =SUM(B24:N24) -> 2345.67
A25: 46162 | B25: 205.22 | C25: 751.8 | D25: 1294.8 | E25: 0 | F25: 0 | G25: 0 | H25: 0 | I25: 0 | J25: 0 | K25: 0 | L25: 44.97 | M25: 109.32 | N25: 0 | O25: =SUM(B25:N25) -> 2406.11
A26: 46163 | B26: 86.2 | C26: 385.41 | D26: 1095.6 | E26: 0 | F26: 0 | G26: 30.59 | H26: 331.94 | I26: 0 | J26: 0 | K26: 30 | L26: 169.87 | M26: 109.32 | N26: 0 | O26: =SUM(B26:N26) -> 2238.93
A27: 46164 | B27: 51 | C27: 90.33 | D27: 896.4 | E27: 0 | F27: 0 | G27: 360.65 | H27: 729.84 | I27: 0 | J27: 0 | K27: 112.5 | L27: 115.95 | M27: 0 | N27: 0 | O27: =SUM(B27:N27) -> 2356.67
A28: 46165 | B28: 97.36 | C28: 410.16 | D28: 298.8 | E28: 0 | F28: 0 | G28: 269.19 | H28: 880.6 | I28: 0 | J28: 0 | K28: 345.5 | L28: 214.97 | M28: 218.64 | N28: 0 | O28: =SUM(B28:N28) -> 2735.22
A29: 46166 | O29: =SUM(B29:N29) -> 0
A30: 46167 | O30: =SUM(B30:N30) -> 0
A31: 46168 | O31: =SUM(B31:N31) -> 0
A32: 46169 | O32: =SUM(B32:N32) -> 0
A33: 46170 | O33: =SUM(B33:N33) -> 0
A34: 46171 | O34: =SUM(B34:N34) -> 0
A35: 46172 | O35: =SUM(B35:N35) -> 0
A36: 46173 | O36: =SUM(B36:N36) -> 0
A37: TOTAL | B37: =SUM(B14:B28) -> 3668.89 | C37: =SUM(C14:C28) -> 6360.79 | D37: =SUM(D14:D28) -> 18524.7 | E37: =SUM(E14:E28) -> 30 | F37: =SUM(F14:F28) -> 0 | G37: =SUM(G14:G28) -> 1701.4 | H37: =SUM(H14:H28) -> 3329.22 | I37: =SUM(I14:I28) -> 1244.5 | ... N37: =SUM(N14:N28) -> 0 | O37: =SUM(B37:N37) -> 43718.22

Sheet Sheet3
A1: RECHARGE REPORTS
B4: AIRTEL | F4: JIO | J4: VI | N4: BSNL | R4: ALL IN 1 | T4: TOTAL
A5: DATE | B5: SALE & P | C5: CHLLAR | D5: ACT | E5: MNP | F5: SALE & P | G5: CHILLAR | H5: ACT | I5: MNP | J5: SALE & P | K5: CHLLAR | L5: ACT | M5: MNP | N5: SALE&P | O5: CHILLAR | P5: ACT | Q5: MNP | R5: SALE & P | S5: CHILLAR
A6: 46143 | B6: 0 | C6: 0 | D6: 0 | E6: 0 | F6: 0 | G6: 0 | H6: 0 | I6: 0 | J6: 0 | K6: 0 | L6: 0 | M6: 0 | N6: 0 | O6: 0 | P6: 0 | Q6: 0 | R6: 0 | S6: 0 | T6: =SUM(B6:S6) -> 0
A7: 46144 | T7: =SUM(B7:S7) -> 0
A8: 46145 | T8: =SUM(B8:S8) -> 0
A9: 46146 | T9: =SUM(B9:S9) -> 0
A10: 46147 | T10: =SUM(B10:S10) -> 0
A11: 46148 | T11: =SUM(B11:S11) -> 0
A12: 46149 | T12: =SUM(B12:S12) -> 0
A13: 46150 | T13: =SUM(B13:S13) -> 0
A14: 46151 | B14: 85.23 | C14: 7 | D14: 0 | E14: 0 | F14: 120 | G14: 9 | H14: 130 | I14: 0 | J14: 15.16 | K14: 4 | L14: 0 | M14: 0 | N14: 0 | O14: 0 | P14: 0 | Q14: 0 | R14: 0 | S14: 0 | T14: =SUM(B14:S14) -> 370.39
A15: 46152 | B15: 70 | C15: 10 | D15: 135 | E15: 0 | F15: 60 | G15: 4 | H15: 0 | I15: 0 | J15: 0 | K15: 4 | L15: 0 | M15: 0 | N15: 0 | O15: 0 | P15: 0 | Q15: 0 | R15: 0 | S15: 0 | T15: =SUM(B15:S15) -> 283
A16: 46153 | B16: 45 | C16: 2 | D16: 0 | E16: 0 | F16: 0 | G16: 10 | H16: 0 | I16: 0 | J16: 159.66 | K16: 5 | L16: 0 | M16: 0 | N16: 0 | O16: 0 | P16: 0 | Q16: 0 | R16: 0 | S16: 0 | T16: =SUM(B16:S16) -> 221.66
A17: 46154 | B17: 15 | C17: 6 | D17: 0 | E17: 0 | F17: 60 | G17: 11 | H17: 227 | I17: 0 | J17: 11.34 | K17: 6 | L17: 0 | M17: 0 | N17: 0 | O17: 0 | P17: 0 | Q17: 0 | R17: 0 | S17: 0 | T17: =SUM(B17:S17) -> 336.34
A18: 46155 | B18: 30 | C18: 5 | D18: 0 | E18: 0 | F18: 120 | G18: 19 | H18: 260 | I18: 0 | J18: 3.32 | K18: 4 | L18: 0 | M18: 0 | N18: 0 | O18: 0 | P18: 0 | Q18: 0 | R18: 0 | S18: 0 | T18: =SUM(B18:S18) -> 441.32
A19: 46156 | B19: 46.47 | C19: 7 | D19: 0 | E19: 0 | F19: 218 | G19: 9 | H19: 130 | I19: 0 | J19: 0 | K19: 4 | L19: 0 | M19: 0 | N19: 0 | O19: 0 | P19: 0 | Q19: 0 | R19: 9.54 | S19: 2 | T19: =SUM(B19:S19) -> 426.01
A20: 46157 | B20: 45 | C20: 6 | D20: 0 | E20: 0 | F20: 60 | G20: 7 | H20: 0 | I20: 0 | J20: 0 | K20: 4 | L20: 0 | M20: 0 | N20: 0 | O20: 0 | P20: 0 | Q20: 0 | R20: 0 | S20: 0 | T20: =SUM(B20:S20) -> 122
A21: 46158 | B21: 128.76 | C21: 8 | D21: 135 | E21: 0 | F21: 60 | G21: 9 | H21: 130 | I21: 0 | J21: 0 | K21: 3 | L21: 250 | M21: 0 | N21: 0 | O21: 0 | P21: 0 | Q21: 0 | R21: 0.12 | S21: 1 | T21: =SUM(B21:S21) -> 724.88
A22: 46159 | B22: 45 | C22: 5 | D22: 0 | E22: 0 | F22: 60 | G22: 11 | H22: 130 | I22: 0 | J22: 11.37 | K22: 4 | L22: 0 | M22: 0 | N22: 0 | O22: 0 | P22: 0 | Q22: 0 | R22: 22.71 | S22: 1 | T22: =SUM(B22:S22) -> 290.08
A23: 46160 | B23: 55.26 | C23: 6 | D23: 0 | E23: 0 | F23: 120 | G23: 16 | H23: 0 | I23: 0 | J23: 150.2 | K23: 6 | L23: 0 | M23: 0 | N23: 0 | O23: 0 | P23: 0 | Q23: 0 | R23: 0 | S23: 0 | T23: =SUM(B23:S23) -> 353.46
A24: 46161 | B24: 60 | C24: 8 | D24: 60 | E24: 0 | F24: 60 | G24: 8 | H24: 0 | I24: 230 | J24: 8.16 | K24: 5 | L24: 0 | M24: 0 | N24: 0 | O24: 0 | P24: 0 | Q24: 0 | R24: 0.06 | S24: 1 | T24: =SUM(B24:S24) -> 440.22
A25: 46162 | B25: 45 | C25: 6 | D25: 0 | E25: 0 | F25: 60 | G25: 15 | H25: 130 | I25: 0 | J25: 0 | K25: 4 | L25: 0 | M25: 0 | N25: 0 | O25: 0 | P25: 0 | Q25: 0 | R25: 60 | S25: 0 | T25: =SUM(B25:S25) -> 320
... A28: 46165 | B28: 100.26 | C28: 9 | D28: 0 | E28: 0 | F28: 120 | G28: 8 | H28: 0 | I28: 0 | J28: 0 | K28: 4 | L28: 0 | M28: 0 | N28: 0 | O28: 0 | P28: 0 | Q28: 0 | R28: 0 | S28: 0 | T28: =SUM(B28:S28) -> 241.26
A29: 46166 | N29: 0 | O29: 0 | P29: 0 | Q29: 0 | T29: =SUM(B29:S29) -> 0
A30: 46167 | N30: 0 | O30: 0 | P30: 0 | Q30: 0 | T30: =SUM(B30:S30) -> 0
A31: 46168 | N31: 0 | O31: 0 | P31: 0 | Q31: 0 | T31: =SUM(B31:S31) -> 0
A32: 46169 | N32: 0 | O32: 0 | P32: 0 | Q32: 0 | T32: =SUM(B32:S32) -> 0
A33: 46170 | N33: 0 | O33: 0 | P33: 0 | Q33: 0 | T33: =SUM(B33:S33) -> 0
A34: 46171 | N34: 0 | O34: 0 | P34: 0 | Q34: 0 | T34: =SUM(B34:S34) -> 0
A35: 46172 | N35: 0 | O35: 0 | P35: 0 | Q35: 0 | T35: =SUM(B35:S35) -> 0
A36: 46173 | N36: 0 | T36: =SUM(B36:S36) -> 0
A37: TOTAL | B37: =SUM(B7:B36) -> 860.98 | C37: =SUM(C7:C36) -> 101 | D37: =SUM(D7:D36) -> 340 | E37: =SUM(E7:E36) -> 0 | F37: =SUM(F7:F36) -> 1358 | G37: =SUM(G7:G36) -> 161 | H37: =SUM(H7:H36) -> 1397 | I37: =SUM(I7:I36) -> 230 | ... S37: =SUM(S7:S36) -> 7 | T37: =SUM(B37:S37) -> 5423.81

Sheet Sheet4
A1: Mobile Accessories & Repairing | K1: EXTRA INCOME
A2: Date | B2: NO. OF REP | C2: SALE | D2: COST | E2: PROFIT | G2: MOBILE & ACC.SALE | H2: Cost | I2: PROFIT | K2: DESCRIPTION | L2: AMOUNT
A3: 46143 | L3: 0
A4: 46144 | L4: 0
A5: 46145 | L5: 0
A6: 46146 | L6: 0
A7: 46147 | L7: 0
A8: 46148 | L8: 0
A9: 46149 | L9: 0
A10: 46150 | L10: 0
A11: 46151 | B11: 8 | C11: 4500 | D11: 2580 | E11: =C11-D11 -> 1920 | G11: 10010 | H11: 2638 | I11: =G11-H11 -> 7372 | L11: 0
A12: 46152 | B12: 6 | C12: 5850 | D12: 2850 | E12: =C12-D12 -> 3000 | G12: 3339 | H12: 1338 | I12: =G12-H12 -> 2001 | L12: 0
A13: 46153 | B13: 10 | C13: 8690 | D13: 4250 | E13: =C13-D13 -> 4440 | G13: 5669 | H13: 2349 | I13: =G13-H13 -> 3320 | L13: 0
A14: 46154 | B14: 3 | C14: 350 | D14: 0 | E14: =C14-D14 -> 350 | G14: 2400 | H14: 876 | I14: =G14-H14 -> 1524 | L14: 0
A15: 46155 | B15: 14 | C15: 6880 | D15: 2725 | E15: =C15-D15 -> 4155 | G15: 6765 | H15: 2535 | I15: =G15-H15 -> 4230 | L15: 0
A16: 46156 | B16: 5 | C16: 2930 | D16: 1600 | E16: =C16-D16 -> 1330 | G16: 4300 | H16: 2543 | I16: =G16-H16 -> 1757 | L16: 0
A17: 46157 | B17: 8 | C17: 9520 | D17: 4520 | E17: =C17-D17 -> 5000 | G17: 2650 | H17: 1356 | I17: =G17-H17 -> 1294 | L17: 0
A18: 46158 | B18: 6 | C18: 2840 | D18: 1330 | E18: =C18-D18 -> 1510 | G18: 3418 | H18: 1134 | I18: =G18-H18 -> 2284 | L18: 0
A19: 46159 | B19: 11 | C19: 9800 | D19: 4940 | E19: =C19-D19 -> 4860 | G19: 4020 | H19: 1265 | I19: =G19-H19 -> 2755 | L19: 0
A20: 46160 | B20: 3 | C20: 1350 | D20: 550 | E20: =C20-D20 -> 800 | G20: 1280 | H20: 475 | I20: =G20-H20 -> 805 | L20: 0
A21: 46161 | B21: 3 | C21: 500 | D21: 0 | E21: =C21-D21 -> 500 | G21: 3700 | H21: 1768 | I21: =G21-H21 -> 1932 | L21: 0
A22: 46162 | B22: 3 | C22: 1300 | D22: 670 | E22: =C22-D22 -> 630 | G22: 3389 | H22: 1317 | I22: =G22-H22 -> 2072 | L22: 0
A23: 46163 | B23: 16 | C23: 12750 | D23: 5780 | E23: =C23-D23 -> 6970 | G23: 4728 | H23: 2115 | I23: =G23-H23 -> 2613 | L23: 0
A24: 46164 | B24: 7 | C24: 4750 | D24: 2300 | E24: =C24-D24 -> 2450 | G24: 3960 | H24: 1726 | I24: =G24-H24 -> 2234 | K24: round figer | L24: 58576
A25: 46165 | B25: 7 | C25: 2480 | D25: 1070 | E25: =C25-D25 -> 1410 | G25: 4789 | H25: 2097 | I25: =G25-H25 -> 2692 | L25: 0
A26: 46166 | E26: =C26-D26 -> 0 | I26: =G26-H26 -> 0 | L26: 0
A27: 46167 | E27: =C27-D27 -> 0 | I27: =G27-H27 -> 0 | L27: 0
A28: 46168 | E28: =C28-D28 -> 0 | I28: =G28-H28 -> 0 | L28: 0
A29: 46169 | E29: =C29-D29 -> 0 | I29: =G29-H29 -> 0 | L29: 0
A30: 46170 | E30: =C30-D30 -> 0 | I30: =G30-H30 -> 0 | L30: 0
A31: 46171 | E31: =C31-D31 -> 0 | I31: =G31-H31 -> 0 | L31: 0
A32: 46172 | E32: =C32-D32 -> 0 | I32: =G32-H32 -> 0 | L32: 0
A33: 46173 | E33: =C33-D33 -> 0 | I33: =G33-H33 -> 0 | L33: 0
A34: TOTAL | B34: =SUM(B11:B33) -> 110 | C34: =SUM(C11:C33) -> 74490 | D34: =SUM(D11:D33) -> 35165 | E34: =SUM(E11:E33) -> 39325 | G34: =SUM(G11:G33) -> 64417 | H34: =SUM(H11:H33) -> 25532 | I34: =SUM(I11:I33) -> 38885 | L34: =SUM(L3:L33) -> 58576

Sheet Sheet5
A1: SHOP EXPENSES | J1: DAMAGE & LOSS
A2: DATE | B2: Descrip | C2: salary | D2: Descrip | E2: Tea & nasta | F2: Descrip | G2: shop exp | H2: TOTAL | J2: Descrip | K2: accessories damage | L2: Descrip | M2: Repairing Damage | N2: amount
A3: 46143 | B3: 0 | C3: 0 | E3: 0 | G3: 0 | H3: =C3+E3+G3 -> 0 | K3: 0 | M3: 0 | N3: =K3+M3 -> 0
A4: 46144 | H4: =C4+E4+G4 -> 0 | N4: =K4+M4 -> 0
A5: 46145 | H5: =C5+E5+G5 -> 0 | N5: =K5+M5 -> 0
A6: 46146 | H6: =C6+E6+G6 -> 0 | N6: =K6+M6 -> 0
A7: 46147 | H7: =C7+E7+G7 -> 0 | N7: =K7+M7 -> 0
A8: 46148 | H8: =C8+E8+G8 -> 0 | N8: =K8+M8 -> 0
A9: 46149 | H9: =C9+E9+G9 -> 0 | N9: =K9+M9 -> 0
A10: 46150 | H10: =C10+E10+G10 -> 0 | N10: =K10+M10 -> 0
A11: 46151 | B11: AYEMAN | C11: 130 | D11: WATER,TEA | E11: 50 | H11: =C11+E11+G11 -> 180 | N11: =K11+M11 -> 0
A12: 46152 | D12: WATER | E12: 40 | H12: =C12+E12+G12 -> 40 | N12: =K12+M12 -> 0
A13: 46153 | D13: WATER,JUICE | E13: 80 | H13: =C13+E13+G13 -> 80 | J13: A6XD+,MATTE PANNI | K13: 65 | N13: =K13+M13 -> 65
A14: 46154 | D14: water nasta | E14: 130 | H14: =C14+E14+G14 -> 130 | J14: 15C D+ | K14: 15 | N14: =K14+M14 -> 15
A15: 46155 | B15: AYEMAN | C15: 30 | D15: nasta pani | E15: 70 | H15: =C15+E15+G15 -> 100 | N15: =K15+M15 -> 0
A16: 46156 | D16: WATER TEA | E16: 30 | H16: =C16+E16+G16 -> 30 | N16: =K16+M16 -> 0
A17: 46157 | H17: =C17+E17+G17 -> 0 | N17: =K17+M17 -> 0
A18: 46158 | H18: =C18+E18+G18 -> 0 | N18: =K18+M18 -> 0
A19: 46159 | D19: WATER | E19: 40 | H19: =C19+E19+G19 -> 40 | N19: =K19+M19 -> 0
A20: 46160 | B20: AFAK | C20: 189 | D20: WATER NASTA | E20: 50 | H20: =C20+E20+G20 -> 239 | N20: =K20+M20 -> 0
A21: 46161 | D21: water nasta | E21: 60 | H21: =C21+E21+G21 -> 60 | N21: =K21+M21 -> 0
A22: 46162 | D22: water,nasta | E22: 60 | H22: =C22+E22+G22 -> 60 | N22: =K22+M22 -> 0
A23: 46163 | D23: water | E23: 40 | H23: =C23+E23+G23 -> 40 | N23: =K23+M23 -> 0
A24: 46164 | D24: water,nasta | E24: 60 | H24: =C24+E24+G24 -> 60 | J24: uv glaas | K24: 60 | N24: =K24+M24 -> 60
A25: 46165 | D25: WATER,NASTA | E25: 80 | H25: =C25+E25+G25 -> 80 | N25: =K25+M25 -> 0
A26: 46166 | H26: =C26+E26+G26 -> 0 | N26: =K26+M26 -> 0
A27: 46167 | H27: =C27+E27+G27 -> 0 | N27: =K27+M27 -> 0
A28: 46168 | H28: =C28+E28+G28 -> 0 | N28: =K28+M28 -> 0
A29: 46169 | H29: =C29+E29+G29 -> 0 | N29: =K29+M29 -> 0
A30: 46170 | H30: =C30+E30+G30 -> 0 | N30: =K30+M30 -> 0
A31: 46171 | H31: =C31+E31+G31 -> 0 | N31: =K31+M31 -> 0
A32: 46172 | H32: =C32+E32+G32 -> 0 | N32: =K32+M32 -> 0
A33: 46173 | H33: =C33+E33+G33 -> 0 | N33: =K33+M33 -> 0
A34: TOTAL | B34: 0 | C34: =SUM(C3:C33) -> 349 | E34: =SUM(E3:E33) -> 790 | G34: 0 | H34: =C34+E34+G34 -> 1139 | K34: 80 | M34: 0 | N34: =K34+M34 -> 80

Sheet Sheet6
A1: PARTY PAYMENT | G1: UDHAR | K1: BANK BALANCE | Q1: WITHDRWAL
B2: PARTY | C2: MATETAILIN | D2: PAYMENT OUT | G2: PAYMENT OUT | H2: PAYMENT IN | I2: TOTAL | K2: DIRECT AC | L2: SALES QR | M2: TRANSFER QR | N2: CASH | O2: TOTAL | P2: DESCRITION | Q2: CASH | R2: BANK | S2: TOTAL
A3: DATE | B3: OUT STANDING | G3: OUT | H3: IN | I3: TOTAL | K3: OPENING | O3: =SUM(K3:N3) -> 0 | Q3: 0 | R3: 0 | S3: =Q3+R3 -> 0
A4: 46143 | K4: 0 | L4: 0 | M4: 0 | N4: 0 | O4: =SUM(K4:N4) -> 0 | S4: =Q4+R4 -> 0
A5: 46144 | O5: =SUM(K5:N5) -> 0 | S5: =Q5+R5 -> 0
A6: 46145 | O6: =SUM(K6:N6) -> 0 | S6: =Q6+R6 -> 0
A7: 46146 | O7: =SUM(K7:N7) -> 0 | S7: =Q7+R7 -> 0
A8: 46147 | O8: =SUM(K8:N8) -> 0 | S8: =Q8+R8 -> 0
A9: 46148 | O9: =SUM(K9:N9) -> 0 | S9: =Q9+R9 -> 0
A10: 46149 | O10: =SUM(K10:N10) -> 0 | S10: =Q10+R10 -> 0
A11: 46150 | L11: 4050 | M11: 10 | O11: =SUM(K11:N11) -> 4060 | S11: =Q11+R11 -> 0
A12: 46151 | K12: 1200 | L12: 3910 | M12: 1025 | O12: =SUM(K12:N12) -> 6135 | S12: =Q12+R12 -> 0
A13: 46152 | K13: 1000 | L13: 6270 | M13: 1290 | O13: =SUM(K13:N13) -> 8560 | S13: =Q13+R13 -> 0
A14: 46153 | K14: 0 | L14: 1590 | M14: 3670 | O14: =SUM(K14:N14) -> 5260 | S14: =Q14+R14 -> 0
A15: 46154 | L15: 4490 | M15: 625 | O15: =SUM(K15:N15) -> 5115 | S15: =Q15+R15 -> 0
A16: 46155 | B16: ONE 7 | C16: 64323 | D16: 20000 | E16: =C16-D16 -> 44323 | K16: 1000 | L16: 9140 | M16: 660 | O16: =SUM(K16:N16) -> 10800 | S16: =Q16+R16 -> 0
A17: 46156 | E17: =C17-D17 -> 0 | K17: 0 | L17: 6330 | M17: 1920 | O17: =SUM(K17:N17) -> 8250 | S17: =Q17+R17 -> 0
A18: 46157 | E18: =C18-D18 -> 0 | K18: 0 | L18: 3110 | M18: 849 | O18: =SUM(K18:N18) -> 3959 | P18: bissi | Q18: 110000 | S18: =Q18+R18 -> 110000
A19: 46158 | E19: =C19-D19 -> 0 | K19: 0 | L19: 3110 | M19: 849 | O19: =SUM(K19:N19) -> 3959 | S19: =Q19+R19 -> 0
A20: 46159 | B20: umesh online | D20: 1200 | E20: =C20-D20 -> -1200 | G20: 32554 | H20: 1000 | I20: =G20-H20 -> 31554 | K20: 1000 | L20: 4590 | M20: 110 | O20: =SUM(K20:N20) -> 5700 | S20: =Q20+R20 -> 0
A21: 46160 | E21: =C21-D21 -> 0 | I21: =G21-H21 -> 0 | K21: 0 | L21: 490 | M21: 1030 | O21: =SUM(K21:N21) -> 1520 | S21: =Q21+R21 -> 0
A22: 46161 | E22: =C22-D22 -> 0 | H22: 900 | I22: =G22-H22 -> -900 | K22: 0 | L22: 6060 | M22: 150 | O22: =SUM(K22:N22) -> 6210 | S22: =Q22+R22 -> 0
A23: 46162 | B23: ONE 7, PURCHASE | C23: 970 | E23: =C23-D23 -> 970 | H23: 1000 | I23: =G23-H23 -> -1000 | L23: 4320 | M23: 1890 | O23: =SUM(K23:N23) -> 6210 | S23: =Q23+R23 -> 0
A24: 46163 | E24: =C24-D24 -> 0 | I24: =G24-H24 -> 0 | L24: 4405 | O24: =SUM(K24:N24) -> 4405 | S24: =Q24+R24 -> 0
A25: 46164 | B25: sagar | C25: 200 | D25: 200 | E25: =C25-D25 -> 0 | H25: 150 | I25: =G25-H25 -> -150 | L25: 6089 | O25: =SUM(K25:N25) -> 6089 | P25: kharcha | Q25: 500 | S25: =Q25+R25 -> 500
A26: 46165 | E26: =C26-D26 -> 0 | H26: 1000 | I26: =G26-H26 -> -1000 | K26: 1000 | L26: 4395 | O26: =SUM(K26:N26) -> 5395 | S26: =Q26+R26 -> 0
A27: 46166 | E27: =C27-D27 -> 0 | G27: 995 | I27: =G27-H27 -> 995 | O27: =SUM(K27:N27) -> 0 | S27: =Q27+R27 -> 0
A28: 46167 | E28: =C28-D28 -> 0 | I28: =G28-H28 -> 0 | O28: =SUM(K28:N28) -> 0 | S28: =Q28+R28 -> 0
A29: 46168 | E29: =C29-D29 -> 0 | I29: =G29-H29 -> 0 | O29: =SUM(K29:N29) -> 0 | S29: =Q29+R29 -> 0
A30: 46169 | E30: =C30-D30 -> 0 | I30: =G30-H30 -> 0 | O30: =SUM(K30:N30) -> 0 | S30: =Q30+R30 -> 0
A31: 46170 | E31: =C31-D31 -> 0 | I31: =G31-H31 -> 0 | O31: =SUM(K31:N31) -> 0 | S31: =Q31+R31 -> 0
A32: 46171 | E32: =C32-D32 -> 0 | I32: =G32-H32 -> 0 | O32: =SUM(K32:N32) -> 0 | S32: =Q32+R32 -> 0
A33: 46172 | E33: =C33-D33 -> 0 | I33: =G33-H33 -> 0 | O33: =SUM(K33:N33) -> 0 | S33: =Q33+R33 -> 0
A34: 46173 | C34: =SUM(C16:C33) -> 65493 | D34: =SUM(D16:D33) -> 21400 | E34: =SUM(E16:E33) -> 44093 | G34: =SUM(G20:G33) -> 33549 | H34: =SUM(H20:H33) -> 4050 | I34: =SUM(I20:I33) -> 29499 | K34: =SUM(K11:K33) -> 5200 | L34: =SUM(L11:L33) -> 72349 | M34: =SUM(M11:M33) -> 14078 | O34: =SUM(K34:N34) -> 91627 | Q34: =SUM(Q3:Q33) -> 110500 | R34: =SUM(R3:R33) -> 0 | S34: =SUM(S3:S33) -> 110500
